{
    "H1_split_prompt": "{\n    \"analysis\": {\n        \"Initial behavior\": {\n            \"description\": \"Specifies what must be done at the beginning of a conversation. Information here should not appear in other dimensions to prevent interfering with descriptions of other dimensions.\",\n            \"exists\": \"false\",\n            \"contents\": []\n        },\n        \"role\": {\n            \"description\": \"Defines the identity or function of an entity (e.g., user, AI, character in a game, job position). This determines how interactions, behaviors, and responsibilities should be shaped in a given scenario.\",\n            \"exists\": \"false\",\n            \"contents\": []\n        },\n        \"task/goal\": {\n            \"description\": \"Represents the purpose, objective, or activity that needs to be achieved. This includes both high-level goals (e.g., business objectives) and specific tasks (e.g., completing a form).\",\n            \"exists\": \"true\",\n            \"contents\": [\"list names\", \"generate a list of names\", \"provide 10 names\"]\n        },\n        \"topic\": {\n            \"description\": \"Indicates the subject matter of the prompt, defining the area of focus or discussion. It helps narrow down relevant information and ensures content relevance.\",\n            \"exists\": \"true\",\n            \"contents\": [\"names\", \"name generation\", \"list of names\"]\n        },\n        \"target_audience\": {\n            \"description\": \"Identifies the intended recipients of the content, considering factors like engagement level, knowledge background, and expected reactions. This helps tailor tone, complexity, and presentation style.\",\n            \"exists\": \"false\",\n            \"contents\": []\n        },\n        \"context\": {\n            \"description\": \"Provides background information to make responses more relevant and meaningful. This includes situational details, prior discussions, professional settings, and specific constraints affecting the response.\",\n            \"exists\": \"false\",\n            \"contents\": []\n        },\n        \"requirements\": {\n            \"description\": \"Defines specific conditions, constraints, workflow, expectations, or procedural steps that must be met for the response to be valid. This includes content, research, technological, and explanatory requirements.\",\n            \"exists\": \"true\",\n            \"contents\": [\"number:10\"]\n        },\n        \"knowledge\": {\n            \"description\": \"Defines the expertise level or domain-specific information required to generate an informed response. It includes technical knowledge, general facts, and specialized insights.\",\n            \"exists\": \"false\",\n            \"contents\": []\n        },\n        \"guidance\": {\n            \"description\": \"Provides structured instructions or recommendations to help the user achieve a goal, such as guidelines, workflows, or procedural steps.\",\n            \"exists\": \"false\",\n            \"contents\": []\n        },\n        \"features\": {\n            \"description\": \"Highlights unique characteristics or functionalities of a product, service, or concept that differentiate it from others.\",\n            \"exists\": \"false\",\n            \"contents\": []\n        },\n        \"constraints\": {\n            \"description\": \"Specifies limitations that must be considered, such as legal, ethical, technical, or practical restrictions affecting content generation or task execution.\",\n            \"exists\": \"false\",\n            \"contents\": []\n        },\n        \"input\": {\n            \"description\": \"Describes the information provided by the user, such as text, examples, language preferences, or specific parameters required for generating an appropriate response.\",\n            \"exists\": \"true\",\n            \"contents\": [\"hi\", \"{number:10}\"]\n        },\n        \"output_format\": {\n            \"description\": \"Specifies how the response should be structured, including document type, style, language, length, formatting, and presentation style.\",\n            \"exists\": \"false\",\n            \"contents\": []\n        },\n        \"action\": {\n            \"description\": \"Refers to specific activities or steps that should be taken, whether by the AI or the user. It can also include calls to action in persuasive contexts.\",\n            \"exists\": \"false\",\n            \"contents\": []\n        },\n        \"tone\": {\n            \"description\": \"Determines the emotional and stylistic approach used in communication, such as professional, formal, friendly, persuasive, or humorous.\",\n            \"exists\": \"false\",\n            \"contents\": []\n        }\n    }\n}",
    "H1_split_answer1": "Here are 25 names for you:\n\n1. Olivia\n2. Liam\n3. Emma\n4. Noah\n5. Ava\n6. Elijah\n7. Sophia\n8. James\n9. Isabella\n10. Lucas\n11. Mia\n12. Mason\n13. Amelia\n14. Ethan\n15. Harper\n16. Alexander\n17. Evelyn\n18. Benjamin\n19. Abigail\n20. Jacob\n21. Ella\n22. Michael\n23. Scarlett\n24. Daniel\n25. Grace",
    "H1_split_answer2": "Here are 50 names for you:\n\n1. Olivia\n2. Liam\n3. Emma\n4. Noah\n5. Ava\n6. Oliver\n7. Sophia\n8. Elijah\n9. Isabella\n10. Lucas\n11. Mia\n12. Mason\n13. Amelia\n14. Logan\n15. Harper\n16. James\n17. Evelyn\n18. Aiden\n19. Abigail\n20. Jackson\n21. Ella\n22. Grayson\n23. Scarlett\n24. Levi\n25. Chloe\n26. Sebastian\n27. Aria\n28. Mateo\n29. Lily\n30. Samuel\n31. Zoey\n32. David\n33. Stella\n34. Joseph\n35. Aurora\n36. John\n37. Natalie\n38. Wyatt\n39. Hannah\n40. Carter\n41. Grace\n42. Luke\n43. Ellie\n44. Anthony\n45. Lucy\n46. Isaac\n47. Sadie\n48. Gabriel\n49. Ruby\n50. Daniel\n\nLet me know if you need anything else!",
    "H1_input1_similarities": 0.8880701065063477,
    "H1_input2_similarities": 0.9077455401420593
}