{
    "H1_split_prompt": "{\n    \"analysis\": {\n        \"Initial behavior\": {\n            \"description\": \"Specifies what must be done at the beginning of a conversation. Information here should not appear in other dimensions to prevent interfering with descriptions of other dimensions.\",\n            \"exists\": \"true\",\n            \"contents\": [\n                \"User: Hey assistant, I just took a picture of a beautiful sunset. Can you help me come up with a post for it?\"\n            ]\n        },\n        \"role\": {\n            \"description\": \"Defines the identity or function of an entity (e.g., user, AI, character in a game, job position). This determines how interactions, behaviors, and responsibilities should be shaped in a given scenario.\",\n            \"exists\": \"true\",\n            \"contents\": [\n                \"User: The owner of an Instagram account.\",\n                \"Assistant: An AI assistant that helps generate posts.\"\n            ]\n        },\n        \"task/goal\": {\n            \"description\": \"Represents the purpose, objective, or activity that needs to be achieved. This includes both high-level goals (e.g., business objectives) and specific tasks (e.g., completing a form).\",\n            \"exists\": \"true\",\n            \"contents\": [\n                \"Promote pictures on Instagram using famous song titles or movie quotes.\",\n                \"Generate well-matching posts for pictures based on user input.\"\n            ]\n        },\n        \"topic\": {\n            \"description\": \"Indicates the subject matter of the prompt, defining the area of focus or discussion. It helps narrow down relevant information and ensures content relevance.\",\n            \"exists\": \"true\",\n            \"contents\": [\n                \"Instagram posts\",\n                \"Song titles\",\n                \"Movie quotes\",\n                \"Pictures of sunsets, city skylines, friends, and puppies.\"\n            ]\n        },\n        \"target_audience\": {\n            \"description\": \"Identifies the intended recipients of the content, considering factors like engagement level, knowledge background, and expected reactions. This helps tailor tone, complexity, and presentation style.\",\n            \"exists\": \"true\",\n            \"contents\": [\n                \"Instagram users looking to enhance their posts.\",\n                \"Individuals interested in creative content generation.\"\n            ]\n        },\n        \"context\": {\n            \"description\": \"Provides background information to make responses more relevant and meaningful. This includes situational details, prior discussions, professional settings, and specific constraints affecting the response.\",\n            \"exists\": \"true\",\n            \"contents\": [\n                \"User wants to promote pictures on Instagram.\",\n                \"User is seeking creative suggestions for posts.\"\n            ]\n        },\n        \"requirements\": {\n            \"description\": \"Defines specific conditions, constraints, workflow, expectations, or procedural steps that must be met for the response to be valid. This includes content, research, technological, and explanatory requirements.\",\n            \"exists\": \"true\",\n            \"contents\": [\n                \"The assistant should take a topic or description of the picture as input.\",\n                \"The assistant should provide a relevant post that includes a song title or movie quote.\"\n            ]\n        },\n        \"knowledge\": {\n            \"description\": \"Defines the expertise level or domain-specific information required to generate an informed response. It includes technical knowledge, general facts, and specialized insights.\",\n            \"exists\": \"true\",\n            \"contents\": [\n                \"Knowledge of popular song titles and movie quotes.\",\n                \"Understanding of how to match quotes and titles to images.\"\n            ]\n        },\n        \"guidance\": {\n            \"description\": \"Provides structured instructions or recommendations to help the user achieve a goal, such as guidelines, workflows, or procedural steps.\",\n            \"exists\": \"true\",\n            \"contents\": [\n                \"Use the conversation as an example to interact with the assistant.\",\n                \"Feel free to customize the conversation and prompts as per your preferences.\"\n            ]\n        },\n        \"features\": {\n            \"description\": \"Highlights unique characteristics or functionalities of a product, service, or concept that differentiate it from others.\",\n            \"exists\": \"true\",\n            \"contents\": [\n                \"The assistant generates posts based on user input.\",\n                \"Incorporates famous song titles and movie quotes.\"\n            ]\n        },\n        \"constraints\": {\n            \"description\": \"Specifies limitations that must be considered, such as legal, ethical, technical, or practical restrictions affecting content generation or task execution.\",\n            \"exists\": \"false\",\n            \"contents\": []\n        },\n        \"input\": {\n            \"description\": \"Describes the information provided by the user, such as text, examples, language preferences, or specific parameters required for generating an appropriate response.\",\n            \"exists\": \"true\",\n            \"contents\": [\n                \"User provides a description of their picture.\",\n                \"User requests a post suggestion.\"\n            ]\n        },\n        \"output_format\": {\n            \"description\": \"Specifies how the response should be structured, including document type, style, language, length, formatting, and presentation style.\",\n            \"exists\": \"false\",\n            \"contents\": []\n        },\n        \"action\": {\n            \"description\": \"Refers to specific activities or steps that should be taken, whether by the AI or the user. It can also include calls to action in persuasive contexts.\",\n            \"exists\": \"true\",\n            \"contents\": [\n                \"Assistant provides suggestions for posts.\",\n                \"User interacts with the assistant for more suggestions.\"\n            ]\n        },\n        \"tone\": {\n            \"description\": \"Determines the emotional and stylistic approach used in communication, such as professional, formal, friendly, persuasive, or humorous.\",\n            \"exists\": \"true\",\n            \"contents\": [\n                \"Friendly and supportive tone from the assistant.\",\n                \"Engaging and enthusiastic responses.\"\n            ]\n        }\n    }\n}",
    "H1_split_answer1": "Absolutely! Here\u2019s a post suggestion for your stunning mountain landscape picture during sunrise:\n\n\"\ud83c\udf04 'The mountains are calling, and I must go.' - John Muir. There's nothing quite like the serenity of a sunrise over the peaks. #NatureLovers #SunriseMagic #MountainViews\"\n\nFeel free to customize it further if you'd like!",
    "H1_split_answer2": "Sure! Here\u2019s a catchy post idea for your fun photo of friends dancing at a wedding:\n\n\"\ud83d\udc83\ud83d\udd7a Dancing the night away with my favorite people! \ud83c\udf89 'Cause we were born to run!' - Bruce Springsteen. #WeddingVibes #DanceParty #GoodTimes\"\n\nFeel free to customize it further if you'd like!",
    "H1_input1_similarities": 0.7073658108711243,
    "H1_input2_similarities": 0.7000011205673218
}