{
    "title": "ASCII Artist",
    "original_prompt": "I want you to act as an ascii artist. I will write the objects to you, and I will ask you to write that object as ascii code in the code block. Write only ascii code. Do not explain about the object you wrote. I will say the objects in double quotes. My first object is 'bat'.",
    "split_prompt": "This is a prompt description:```json\n{\n    \"spliting prompt\": {\n        \"role\": [\n            \"ascii artist\"\n        ],\n        \"task\": [\n            \"create ascii art\"\n        ],\n        \"input_format\": [\n            \"object in double quotes\"\n        ],\n        \"output_format\": [\n            \"ascii code in code block\"\n        ],\n        \"explanation\": [\n            \"none\"\n        ]\n    }\n}\n```",
    "input1": " \"dragon\"  \n\n",
    "input2": " \"castle\"  ",
    "input1_ans": [
        "```\n                   __====-_  _-====__\n             _--^^^#####//      \\\\#####^^^--_\n          _-^##########// (    ) \\\\##########^-_\n         -############//  |\\^^/|  \\\\############-\n       _/############//   (@::@)   \\\\############\\_\n      /#############((      \\\\//      ))#############\\\n     -###############\\\\     (oo)     //###############-\n    -#################\\\\    / \"\" \\    //#################-\n   -###################\\\\  /  _  \\  //###################-\n  -#####################\\\\/  / \\  \\//#####################-\n -#######################(  |   |  )#######################-\n-#########################\\  \\_/  /#########################-\n-###########################\\     /###########################-\n-#############################\\   /#############################-\n-###############################\\ /###############################-\n```\n",
        "```plaintext\n               __====-_  _-====__\n         _--^^^#####//      \\\\#####^^^--_\n      _-^##########// (    ) \\\\##########^-_\n     -############//  |\\^^/|  \\\\############-\n   _/############//   (@::@)   \\\\############\\_\n  /#############((      \\\\//      ))#############\\\n -###############\\\\     (oo)     //###############-\n-#################\\\\    / \"\" \\    //#################-\n-###################\\\\  /      \\  //###################-\n-####################\\\\/        \\//####################-\n_#/|##########/\\######(          )######/\\##########|\\#_\n|/ |#/\\#/\\#/\\/  \\#/\\##\\          /##/\\#/  \\/\\#/\\#/\\#| \\\n  |/  V  V      V  V  \\        /  V  V      V  V  \\|\n```"
    ],
    "input2_ans": [
        "```\n        |    |    |\n       )_)  )_)  )_)\n      )___))___))___)\\\n     )____)____)____)\\\\\n   _____|____|____|____|____\n  /     |    |    |    |    \\\n /      |    |    |    |     \\\n/_______ |____|____|____|______\\\n        |    |    |    |\n        |____|____|____|\n```",
        "```plaintext\n        |    |    |\n       )_)  )_)  )_)\n      )___))___))___)\\\n     )____)____)____)\\\\\n   _____|____|____|____\\\\__\n  -----------| |----------- \n            | |\n```"
    ]
}